{"trial_id": "5420d15649592b5d451eae6b425e9f55", "hyperparameters": {"space": [{"class_name": "Boolean", "config": {"name": "structured_data_block_1/normalize", "default": false, "conditions": []}}, {"class_name": "Boolean", "config": {"name": "structured_data_block_1/dense_block_1/use_batchnorm", "default": false, "conditions": []}}, {"class_name": "Choice", "config": {"name": "structured_data_block_1/dense_block_1/num_layers", "default": 2, "conditions": [], "values": [1, 2, 3], "ordered": true}}, {"class_name": "Choice", "config": {"name": "structured_data_block_1/dense_block_1/units_0", "default": 32, "conditions": [], "values": [16, 32, 64, 128, 256, 512, 1024], "ordered": true}}, {"class_name": "Choice", "config": {"name": "structured_data_block_1/dense_block_1/dropout", "default": 0.0, "conditions": [], "values": [0.0, 0.25, 0.5], "ordered": true}}, {"class_name": "Choice", "config": {"name": "structured_data_block_1/dense_block_1/units_1", "default": 32, "conditions": [], "values": [16, 32, 64, 128, 256, 512, 1024], "ordered": true}}, {"class_name": "Choice", "config": {"name": "classification_head_1/dropout", "default": 0, "conditions": [], "values": [0.0, 0.25, 0.5], "ordered": true}}, {"class_name": "Choice", "config": {"name": "optimizer", "default": "adam", "conditions": [], "values": ["adam", "sgd", "adam_weight_decay"], "ordered": false}}, {"class_name": "Choice", "config": {"name": "learning_rate", "default": 0.001, "conditions": [], "values": [0.1, 0.01, 0.001, 0.0001, 2e-05, 1e-05], "ordered": true}}, {"class_name": "Choice", "config": {"name": "structured_data_block_1/dense_block_1/units_2", "default": 32, "conditions": [], "values": [16, 32, 64, 128, 256, 512, 1024], "ordered": true}}], "values": {"structured_data_block_1/normalize": true, "structured_data_block_1/dense_block_1/use_batchnorm": false, "structured_data_block_1/dense_block_1/num_layers": 2, "structured_data_block_1/dense_block_1/units_0": 32, "structured_data_block_1/dense_block_1/dropout": 0, "structured_data_block_1/dense_block_1/units_1": 32, "classification_head_1/dropout": 0.25, "optimizer": "adam", "learning_rate": 0.001, "structured_data_block_1/dense_block_1/units_2": 512}}, "metrics": {"metrics": {"loss": {"direction": "min", "observations": [{"value": [0.7470775842666626], "step": 0}, {"value": [0.6674216389656067], "step": 1}, {"value": [0.6210834383964539], "step": 2}, {"value": [0.5719898343086243], "step": 3}, {"value": [0.5501559972763062], "step": 4}, {"value": [0.5137876868247986], "step": 5}, {"value": [0.4943646192550659], "step": 6}, {"value": [0.4801732897758484], "step": 7}, {"value": [0.46464425325393677], "step": 8}, {"value": [0.4505328834056854], "step": 9}, {"value": [0.4529566168785095], "step": 10}, {"value": [0.4573196768760681], "step": 11}, {"value": [0.442311555147171], "step": 12}, {"value": [0.4409940540790558], "step": 13}, {"value": [0.43185222148895264], "step": 14}, {"value": [0.44039642810821533], "step": 15}, {"value": [0.4218733012676239], "step": 16}, {"value": [0.4210011959075928], "step": 17}, {"value": [0.42919912934303284], "step": 18}, {"value": [0.41755998134613037], "step": 19}, {"value": [0.4237920045852661], "step": 20}, {"value": [0.4204535186290741], "step": 21}, {"value": [0.4097142219543457], "step": 22}, {"value": [0.4144550561904907], "step": 23}, {"value": [0.40137800574302673], "step": 24}, {"value": [0.4195956289768219], "step": 25}, {"value": [0.40748128294944763], "step": 26}, {"value": [0.41193294525146484], "step": 27}, {"value": [0.4050993323326111], "step": 28}, {"value": [0.4066520035266876], "step": 29}, {"value": [0.4116557538509369], "step": 30}, {"value": [0.4072977900505066], "step": 31}, {"value": [0.3998338580131531], "step": 32}, {"value": [0.3915374279022217], "step": 33}, {"value": [0.3986254334449768], "step": 34}, {"value": [0.40105974674224854], "step": 35}, {"value": [0.39369261264801025], "step": 36}, {"value": [0.40506789088249207], "step": 37}, {"value": [0.3988553285598755], "step": 38}, {"value": [0.3987536132335663], "step": 39}]}, "accuracy": {"direction": "max", "observations": [{"value": [0.40234375], "step": 0}, {"value": [0.607421875], "step": 1}, {"value": [0.697265625], "step": 2}, {"value": [0.75390625], "step": 3}, {"value": [0.73828125], "step": 4}, {"value": [0.78515625], "step": 5}, {"value": [0.802734375], "step": 6}, {"value": [0.80859375], "step": 7}, {"value": [0.80859375], "step": 8}, {"value": [0.81640625], "step": 9}, {"value": [0.814453125], "step": 10}, {"value": [0.81640625], "step": 11}, {"value": [0.806640625], "step": 12}, {"value": [0.818359375], "step": 13}, {"value": [0.830078125], "step": 14}, {"value": [0.8203125], "step": 15}, {"value": [0.830078125], "step": 16}, {"value": [0.8203125], "step": 17}, {"value": [0.8125], "step": 18}, {"value": [0.818359375], "step": 19}, {"value": [0.818359375], "step": 20}, {"value": [0.814453125], "step": 21}, {"value": [0.822265625], "step": 22}, {"value": [0.822265625], "step": 23}, {"value": [0.837890625], "step": 24}, {"value": [0.806640625], "step": 25}, {"value": [0.82421875], "step": 26}, {"value": [0.8203125], "step": 27}, {"value": [0.828125], "step": 28}, {"value": [0.822265625], "step": 29}, {"value": [0.826171875], "step": 30}, {"value": [0.84375], "step": 31}, {"value": [0.833984375], "step": 32}, {"value": [0.83203125], "step": 33}, {"value": [0.845703125], "step": 34}, {"value": [0.830078125], "step": 35}, {"value": [0.833984375], "step": 36}, {"value": [0.828125], "step": 37}, {"value": [0.830078125], "step": 38}, {"value": [0.830078125], "step": 39}]}, "val_loss": {"direction": "min", "observations": [{"value": [0.6882893443107605], "step": 0}, {"value": [0.6224368810653687], "step": 1}, {"value": [0.570965588092804], "step": 2}, {"value": [0.5253131985664368], "step": 3}, {"value": [0.48372602462768555], "step": 4}, {"value": [0.44881197810173035], "step": 5}, {"value": [0.4249483048915863], "step": 6}, {"value": [0.4057686924934387], "step": 7}, {"value": [0.3932909369468689], "step": 8}, {"value": [0.38405776023864746], "step": 9}, {"value": [0.3801809847354889], "step": 10}, {"value": [0.37873876094818115], "step": 11}, {"value": [0.37467435002326965], "step": 12}, {"value": [0.36975783109664917], "step": 13}, {"value": [0.3669283092021942], "step": 14}, {"value": [0.3652900159358978], "step": 15}, {"value": [0.3638296127319336], "step": 16}, {"value": [0.36299070715904236], "step": 17}, {"value": [0.36330389976501465], "step": 18}, {"value": [0.36396524310112], "step": 19}, {"value": [0.3643050491809845], "step": 20}, {"value": [0.3628598749637604], "step": 21}, {"value": [0.36382168531417847], "step": 22}, {"value": [0.3619072437286377], "step": 23}, {"value": [0.36152857542037964], "step": 24}, {"value": [0.3620881140232086], "step": 25}, {"value": [0.3603147864341736], "step": 26}, {"value": [0.3597131371498108], "step": 27}, {"value": [0.35943326354026794], "step": 28}, {"value": [0.3589780032634735], "step": 29}, {"value": [0.3600873053073883], "step": 30}, {"value": [0.3603946268558502], "step": 31}, {"value": [0.35982978343963623], "step": 32}, {"value": [0.3591541349887848], "step": 33}, {"value": [0.3611060678958893], "step": 34}, {"value": [0.3618440330028534], "step": 35}, {"value": [0.3602863550186157], "step": 36}, {"value": [0.36274129152297974], "step": 37}, {"value": [0.36176061630249023], "step": 38}, {"value": [0.36201125383377075], "step": 39}]}, "val_accuracy": {"direction": "max", "observations": [{"value": [0.5043478012084961], "step": 0}, {"value": [0.7652173638343811], "step": 1}, {"value": [0.800000011920929], "step": 2}, {"value": [0.800000011920929], "step": 3}, {"value": [0.8173912763595581], "step": 4}, {"value": [0.8173912763595581], "step": 5}, {"value": [0.8173912763595581], "step": 6}, {"value": [0.8173912763595581], "step": 7}, {"value": [0.834782600402832], "step": 8}, {"value": [0.852173924446106], "step": 9}, {"value": [0.843478262424469], "step": 10}, {"value": [0.852173924446106], "step": 11}, {"value": [0.852173924446106], "step": 12}, {"value": [0.843478262424469], "step": 13}, {"value": [0.843478262424469], "step": 14}, {"value": [0.843478262424469], "step": 15}, {"value": [0.852173924446106], "step": 16}, {"value": [0.834782600402832], "step": 17}, {"value": [0.834782600402832], "step": 18}, {"value": [0.834782600402832], "step": 19}, {"value": [0.843478262424469], "step": 20}, {"value": [0.852173924446106], "step": 21}, {"value": [0.852173924446106], "step": 22}, {"value": [0.843478262424469], "step": 23}, {"value": [0.843478262424469], "step": 24}, {"value": [0.843478262424469], "step": 25}, {"value": [0.843478262424469], "step": 26}, {"value": [0.843478262424469], "step": 27}, {"value": [0.843478262424469], "step": 28}, {"value": [0.843478262424469], "step": 29}, {"value": [0.843478262424469], "step": 30}, {"value": [0.843478262424469], "step": 31}, {"value": [0.843478262424469], "step": 32}, {"value": [0.843478262424469], "step": 33}, {"value": [0.843478262424469], "step": 34}, {"value": [0.843478262424469], "step": 35}, {"value": [0.843478262424469], "step": 36}, {"value": [0.843478262424469], "step": 37}, {"value": [0.843478262424469], "step": 38}, {"value": [0.843478262424469], "step": 39}]}}}, "score": 0.852173924446106, "best_step": 9, "status": "COMPLETED"}